{
    "level": "3D",
    "currentState": "LaserTrigger",
    "startTime": 44631828,
    "stopTime": 44638562,
    "gazePoints": [],
    "action": [
        "44633201,4,True",
        "44634989,5,True",
        "44636205,7,True",
        "44638562,11,True"
    ],
    "scaling": "Large",
    "buttonPositionLabel": [
        1,
        16,
        13,
        12,
        7,
        3,
        9,
        14,
        15,
        2,
        11,
        8,
        5,
        10,
        6,
        4
    ],
    "buttonPosition": [
        5.0,
        0.000009999999747378752,
        2.246112585067749,
        0.7272829413414002,
        2.397597074508667,
        4.600363254547119,
        2.3191895484924318,
        3.1490817070007326,
        4.160762786865234,
        2.5160014629364015,
        4.704426288604736,
        4.085844993591309,
        3.8426132202148439,
        2.0556416511535646,
        3.1279149055480959,
        2.4201996326446535
    ]
}