{
    "level": "3D",
    "currentState": "LaserTrigger",
    "startTime": 44564308,
    "stopTime": 44570718,
    "gazePoints": [],
    "action": [
        "44566531,6,True",
        "44567613,3,True",
        "44569311,14,True",
        "44570718,8,True"
    ],
    "scaling": "Large",
    "buttonPositionLabel": [
        1,
        16,
        10,
        9,
        8,
        13,
        12,
        4,
        2,
        7,
        6,
        3,
        5,
        15,
        14,
        11
    ],
    "buttonPosition": [
        5.0,
        0.000009999999747378752,
        1.6739819049835206,
        4.508058547973633,
        2.884026527404785,
        4.463945388793945,
        3.022639274597168,
        4.911105632781982,
        2.3160784244537355,
        2.0482053756713869,
        0.09722736477851868,
        2.622636318206787,
        2.752917528152466,
        3.259286880493164,
        1.4050135612487794,
        1.0890061855316163
    ]
}