{
    "level": "Fitts Law near",
    "currentState": "EyeTrigger",
    "startTime": 54037003,
    "stopTime": 54052337,
    "gazePoints": [
        "(-2.3, 2.3, -2.5)",
        "(-0.5, 1.4, -2.5)",
        "(0.4, 1.0, -2.5)",
        "(-0.3, 0.7, -2.5)",
        "(-0.4, 0.5, -2.5)",
        "(-0.5, 1.3, -2.5)",
        "(1.1, 0.7, -2.5)",
        "(1.2, 0.6, -2.5)",
        "(1.3, 0.5, -2.5)",
        "(1.3, 0.3, -2.5)",
        "(-0.3, 1.9, -2.5)",
        "(-1.1, 1.7, -2.5)",
        "(-0.6, 2.2, -2.5)",
        "(-1.2, 1.8, -2.5)",
        "(-1.3, 1.9, -2.5)",
        "(-0.4, 1.9, -2.5)"
    ],
    "action": [
        "54038284,7,True",
        "54041294,15,True",
        "54044065,-1,False",
        "54045940,13,True",
        "54050650,-1,False",
        "54051250,4,True",
        "54052336,3,True"
    ],
    "scaling": "Large"
}